sphericalHarmonicDecomposition/__init__.py
sphericalHarmonicDecomposition/__main__.py
sphericalHarmonicDecomposition-1.0.3.dist-info/LICENSE
sphericalHarmonicDecomposition-1.0.3.dist-info/METADATA
sphericalHarmonicDecomposition-1.0.3.dist-info/WHEEL
sphericalHarmonicDecomposition-1.0.3.dist-info/top_level.txt
sphericalHarmonicDecomposition-1.0.3.dist-info/RECORD
