Metadata-Version: 2.1
Name: sphericalHarmonicDecomposition
Version: 1.0.3
Author-email: Pablo Ibáñez-Freire <p.ibanez.fre@gmail.com>
License: GPL-3.0-or-later
Project-URL: Homepage, https://github.com/PabloIbannez/sphericalHarmonicDecomposition
Project-URL: Bug Tracker, https://github.com/PabloIbannez/sphericalHarmonicDecomposition/issues
Classifier: Development Status :: 3 - Alpha
Classifier: License :: OSI Approved :: MIT License
Classifier: Programming Language :: Python :: 3
Classifier: Programming Language :: Python :: 3.7
Classifier: Programming Language :: Python :: 3.8
Classifier: Programming Language :: Python :: 3.9
Requires-Python: >=3.7
License-File: LICENSE
Requires-Dist: tqdm
Requires-Dist: matplotlib
Requires-Dist: numpy
Requires-Dist: icosphere
Requires-Dist: orthopoly
Requires-Dist: MDAnalysis
Requires-Dist: scipy
